[
  {
    "value": "保濕",
    "synonyms": [
      "保濕"
    ]
  },
  {
    "value": "滋潤",
    "synonyms": [
      "滋潤",
      "水潤"
    ]
  },
  {
    "value": "修護",
    "synonyms": [
      "修護",
      "修復"
    ]
  },
  {
    "value": "潤色",
    "synonyms": [
      "潤色"
    ]
  },
  {
    "value": "修飾毛孔",
    "synonyms": [
      "修飾毛孔",
      "毛孔修飾"
    ]
  },
  {
    "value": "遮瑕",
    "synonyms": [
      "遮瑕"
    ]
  },
  {
    "value": "修正膚色",
    "synonyms": [
      "修正膚色",
      "膚色修正"
    ]
  },
  {
    "value": "透亮",
    "synonyms": [
      "透亮",
      "亮透"
    ]
  },
  {
    "value": "長效持妝",
    "synonyms": [
      "長效持妝",
      "持妝",
      "持妝久",
      "維持妝容",
      "不會掉色",
      "不掉色",
      "不容易掉色"
    ]
  },
  {
    "value": "薄透",
    "synonyms": [
      "薄透",
      "輕薄"
    ]
  },
  {
    "value": "好上色",
    "synonyms": [
      "好上色",
      "容易上色",
      "易上色"
    ]
  },
  {
    "value": "色彩飽和",
    "synonyms": [
      "色彩飽和"
    ]
  },
  {
    "value": "抗暈染",
    "synonyms": [
      "抗暈染",
      "防暈",
      "抗暈",
      "不會暈染",
      "不暈染",
      "不暈",
      "不會暈開",
      "不會暈"
    ]
  },
  {
    "value": "纖長",
    "synonyms": [
      "纖長",
      "細長"
    ]
  },
  {
    "value": "根根分明",
    "synonyms": [
      "根根分明"
    ]
  },
  {
    "value": "顯色",
    "synonyms": [
      "顯色",
      "顏色明顯",
      "色彩明顯"
    ]
  },
  {
    "value": "好推勻",
    "synonyms": [
      "好推勻",
      "容易推勻",
      "好推開",
      "好推",
      "易推"
    ]
  },
  {
    "value": "細緻",
    "synonyms": [
      "細緻"
    ]
  },
  {
    "value": "修容",
    "synonyms": [
      "修容"
    ]
  },
  {
    "value": "美白",
    "synonyms": [
      "美白",
      "變白"
    ]
  },
  {
    "value": "提升光澤",
    "synonyms": [
      "提升光澤",
      "增加光澤"
    ]
  },
  {
    "value": "平滑膚觸",
    "synonyms": [
      "平滑膚觸"
    ]
  },
  {
    "value": "抗氧化",
    "synonyms": [
      "抗氧化"
    ]
  },
  {
    "value": "舒緩",
    "synonyms": [
      "舒緩"
    ]
  },
  {
    "value": "清爽",
    "synonyms": [
      "清爽",
      "不油膩",
      "不油不膩",
      "不油"
    ]
  },
  {
    "value": "抗老",
    "synonyms": [
      "抗老"
    ]
  },
  {
    "value": "緊實",
    "synonyms": [
      "緊實"
    ]
  },
  {
    "value": "拉提",
    "synonyms": [
      "拉提"
    ]
  },
  {
    "value": "細緻毛孔",
    "synonyms": [
      "細緻毛孔"
    ]
  },
  {
    "value": "香氛",
    "synonyms": [
      "香氛",
      "香氣",
      "香味"
    ]
  },
  {
    "value": "服貼",
    "synonyms": [
      "服貼"
    ]
  },
  {
    "value": "光澤",
    "synonyms": [
      "光澤",
      "有光澤",
      "光澤感"
    ]
  },
  {
    "value": "均勻膚色",
    "synonyms": [
      "均勻膚色",
      "膚色均勻"
    ]
  },
  {
    "value": "防曬",
    "synonyms": [
      "防曬"
    ]
  },
  {
    "value": "抗皺",
    "synonyms": [
      "抗皺",
      "除皺紋"
    ]
  },
  {
    "value": "改善細紋",
    "synonyms": [
      "改善細紋",
      "細紋消失",
      "除細紋",
      "細紋減少"
    ]
  },
  {
    "value": "清潔",
    "synonyms": [
      "清潔",
      "清洗"
    ]
  },
  {
    "value": "控油",
    "synonyms": [
      "控油",
      "不出油"
    ]
  },
  {
    "value": "珠光",
    "synonyms": [
      "珠光"
    ]
  },
  {
    "value": "卸妝",
    "synonyms": [
      "卸妝"
    ]
  },
  {
    "value": "防水",
    "synonyms": [
      "防水"
    ]
  },
  {
    "value": "不黏膩",
    "synonyms": [
      "不黏膩",
      "不黏",
      "不膩"
    ]
  },
  {
    "value": "溫和低刺激",
    "synonyms": [
      "溫和低刺激",
      "溫和",
      "低刺激",
      "不刺激",
      "沒有刺激性",
      "無刺激性"
    ]
  },
  {
    "value": "好吸收",
    "synonyms": [
      "好吸收",
      "容易吸收",
      "吸收效果好",
      "快速吸收"
    ]
  },
  {
    "value": "淡斑",
    "synonyms": [
      "淡斑",
      "斑",
      "雀斑"
    ]
  },
  {
    "value": "去角質",
    "synonyms": [
      "去角質"
    ]
  },
  {
    "value": "深層清潔",
    "synonyms": [
      "深層清潔"
    ]
  },
  {
    "value": "柔順",
    "synonyms": [
      "柔順"
    ]
  },
  {
    "value": "亮澤",
    "synonyms": [
      "亮澤"
    ]
  },
  {
    "value": "防油",
    "synonyms": [
      "防油"
    ]
  },
  {
    "value": "霧面",
    "synonyms": [
      "霧面"
    ]
  },
  {
    "value": "亮面",
    "synonyms": [
      "亮面"
    ]
  },
  {
    "value": "收斂毛孔",
    "synonyms": [
      "收斂毛孔",
      "毛孔收斂",
      "毛孔變小",
      "毛孔縮小",
      "縮小毛孔"
    ]
  },
  {
    "value": "捲翹",
    "synonyms": [
      "捲翹",
      "變翹",
      "翹睫毛",
      "睫毛翹",
      "睫毛捲",
      "翹捲"
    ]
  },
  {
    "value": "濃密",
    "synonyms": [
      "濃密",
      "濃黑",
      "睫毛濃"
    ]
  },
  {
    "value": "打亮",
    "synonyms": [
      "打亮"
    ]
  },
  {
    "value": "溫水可卸",
    "synonyms": [
      "溫水可卸",
      "用溫水卸",
      "溫水可以卸",
      "溫水卸妝"
    ]
  },
  {
    "value": "強韌髮絲",
    "synonyms": [
      "強韌髮絲"
    ]
  },
  {
    "value": "豐盈",
    "synonyms": [
      "豐盈"
    ]
  },
  {
    "value": "抗痘",
    "synonyms": [
      "抗痘",
      "改善痘痘",
      "消除痘痘",
      "除痘"
    ]
  },
  {
    "value": "改善粉刺",
    "synonyms": [
      "改善粉刺",
      "粉刺改善",
      "消除粉刺",
      "除粉刺",
      "去粉刺",
      "消粉刺",
      "拔粉刺",
      "掉粉刺",
      "治粉刺",
      "減少粉刺",
      "粉刺不見"
    ]
  },
  {
    "value": "不致痘",
    "synonyms": [
      "不致痘",
      "不長痘",
      "不會長痘",
      "不會冒痘",
      "不冒痘",
      "不容易長痘",
      "不容易有痘",
      "不容易冒痘"
    ]
  },
  {
    "value": "不致粉刺",
    "synonyms": [
      "不致粉刺",
      "不長粉刺",
      "不會長粉刺",
      "不會冒粉刺",
      "不冒粉刺",
      "不容易長粉刺",
      "不容易有粉刺",
      "不容易冒粉刺"
    ]
  },
  {
    "value": "抗空汙",
    "synonyms": [
      "抗空汙"
    ]
  },
  {
    "value": "改善水腫",
    "synonyms": [
      "改善水腫",
      "消水腫"
    ]
  },
  {
    "value": "改善紋路",
    "synonyms": [
      "改善紋路"
    ]
  },
  {
    "value": "光滑",
    "synonyms": [
      "光滑"
    ]
  },
  {
    "value": "護色",
    "synonyms": [
      "護色"
    ]
  },
  {
    "value": "快乾",
    "synonyms": [
      "快乾"
    ]
  },
  {
    "value": "預防落髮",
    "synonyms": [
      "預防落髮"
    ]
  },
  {
    "value": "飽和色",
    "synonyms": [
      "飽和色",
      "顏色飽和",
      "色彩飽和"
    ]
  },
  {
    "value": "漆亮感",
    "synonyms": [
      "漆亮感"
    ]
  },
  {
    "value": "果凍色",
    "synonyms": [
      "果凍色"
    ]
  },
  {
    "value": "抗屑",
    "synonyms": [
      "抗屑",
      "沒頭皮屑",
      "除頭皮屑",
      "抗頭皮屑"
    ]
  }
]